README.txt
setup.py
django_dynamic_validation.egg-info/PKG-INFO
django_dynamic_validation.egg-info/SOURCES.txt
django_dynamic_validation.egg-info/dependency_links.txt
django_dynamic_validation.egg-info/not-zip-safe
django_dynamic_validation.egg-info/requires.txt
django_dynamic_validation.egg-info/top_level.txt
dynamic_validation/__init__.py
dynamic_validation/admin.py
dynamic_validation/dynamic_actions.py
dynamic_validation/models.py
dynamic_validation/migrations/0001_initial.py
dynamic_validation/migrations/0002_auto__add_field_violation_silent.py
dynamic_validation/migrations/0003_auto__del_field_violation_silent.py
dynamic_validation/migrations/__init__.py
dynamic_validation/templatetags/__init__.py
dynamic_validation/templatetags/dynamic_validation_tags.py
dynamic_validation/tests/__init__.py
dynamic_validation/tests/test_dynamic_actions.py
dynamic_validation/tests/test_models.py
dynamic_validation/tests/test_templatetags.py
dynamic_validation/tests/utils.py
example/sample/__init__.py
example/sample/admin.py
example/sample/dynamic_actions.py
example/sample/models.py
example/sample/views.py