Metadata-Version: 1.1
Name: django-dynamic-validation
Version: 1.2.3
Summary: Define user generated validation requirements for django models.
Home-page: https://github.com/imtapps/django-dynamic-validation
Author: IMT Computer Services
Author-email: webadmin@imtapps.com
License: UNKNOWN
Platform: UNKNOWN
Classifier: Development Status :: 3 - Alpha
Classifier: Environment :: Web Environment
Classifier: Framework :: Django
Classifier: Intended Audience :: Developers
Classifier: License :: OSI Approved :: BSD License
Classifier: Operating System :: OS Independent
Classifier: Programming Language :: Python
Classifier: Topic :: Software Development
Classifier: Topic :: Software Development :: Libraries :: Application Frameworks
